gptchat/__init__.py
gptchat/app.py
gptchat/util/__init__.py
gptchat/util/openai_util.py
gptchat/util/serve.py
static/favicon.svg
static/index.html
static/assets/Chat-DufRpBh3.js
static/assets/Chat-DufRpBh3.js.br
static/assets/Chat-DufRpBh3.js.gz
static/assets/index-vV0AxcPn.js
static/assets/index-vV0AxcPn.js.br
static/assets/index-vV0AxcPn.js.gz
static/assets/style-Th1YKAwy.css
static/assets/style-Th1YKAwy.css.br
static/assets/style-Th1YKAwy.css.gz
gptchat-0.0.12.dist-info/METADATA
gptchat-0.0.12.dist-info/WHEEL
gptchat-0.0.12.dist-info/licenses/LICENSE
gptchat-0.0.12.dist-info/RECORD
