Metadata-Version: 2.1
Name: gptchat
Version: 0.0.12
Summary: A local ChatGPT interface
Author-email: Ryan Young <dev@ryayoung.com>
License-Expression: MIT
License-File: LICENSE
Classifier: Development Status :: 3 - Alpha
Classifier: Intended Audience :: Developers
Classifier: License :: OSI Approved :: MIT License
Classifier: Operating System :: OS Independent
Classifier: Programming Language :: Python :: 3.11
Classifier: Topic :: Software Development :: Libraries
Requires-Dist: eventlet
Requires-Dist: flask-socketio
Requires-Dist: openai[datalib]>=1.0.0
Requires-Dist: pydantic>=2.0
Requires-Dist: requests
